rm2trash/__init__.py
rm2trash/commands/__init__.py
rm2trash/commands/rm2trash.py
rm2trash/commands/subcommands.py
rm2trash/core/__init__.py
rm2trash/core/global_variables.py
rm2trash/core/logging.py
rm2trash/core/trash_manager.py
rm2trash-0.1.1.dist-info/entry_points.txt
rm2trash-0.1.1.dist-info/WHEEL
rm2trash-0.1.1.dist-info/METADATA
rm2trash-0.1.1.dist-info/RECORD
